pydemic/__init__.py
pydemic/all.py
pydemic/cache.py
pydemic/config.py
pydemic/db.py
pydemic/docs.py
pydemic/jupyter.py
pydemic/logging.py
pydemic/packages.py
pydemic/testing.py
pydemic/types.py
pydemic/api/__init__.py
pydemic/api/covid19.py
pydemic/cli/__init__.py
pydemic/cli/api.py
pydemic/cli/main.py
pydemic/clinical_models/__init__.py
pydemic/clinical_models/crude_FR.py
pydemic/clinical_models/hospitalization_with_delay.py
pydemic/clinical_models/hospitalization_with_overflow.py
pydemic/clinical_models/model.py
pydemic/clinical_models/utils.py
pydemic/databases/diseases/covid-19/hospitalization-table-verity.csv
pydemic/databases/diseases/covid-19/mortality-table-verity.csv
pydemic/databases/diseases/covid-19/mortality-table-verity.txt
pydemic/databases/diseases/covid-19/parameters.xls
pydemic/databases/diseases/empty/hospitalization-table-default.csv
pydemic/databases/diseases/empty/mortality-table-default.csv
pydemic/diseases/__init__.py
pydemic/diseases/covid19_class.py
pydemic/diseases/disease_class.py
pydemic/diseases/disease_params.py
pydemic/diseases/utils.py
pydemic/fitting/K.py
pydemic/fitting/R0.py
pydemic/fitting/Rt.py
pydemic/fitting/__init__.py
pydemic/fitting/epidemic_curves.py
pydemic/fitting/epidemic_curves_rt.py
pydemic/fitting/exponential_growth.py
pydemic/fitting/seasonal.py
pydemic/fitting/smoothing.py
pydemic/fitting/time_dependent_growth.py
pydemic/fitting/utils.py
pydemic/formulas/__init__.py
pydemic/formulas/base.py
pydemic/formulas/seair.py
pydemic/formulas/seir.py
pydemic/formulas/sir.py
pydemic/mixins/__init__.py
pydemic/mixins/base_attr.py
pydemic/mixins/data_transforms.py
pydemic/mixins/info.py
pydemic/mixins/meta_info.py
pydemic/mixins/params_info.py
pydemic/mixins/results.py
pydemic/mixins/with_data.py
pydemic/mixins/with_info.py
pydemic/mixins/with_params.py
pydemic/mixins/with_region.py
pydemic/mixins/with_results.py
pydemic/model_group/__init__.py
pydemic/model_group/model_group.py
pydemic/model_group/model_list.py
pydemic_models-0.1.11.dist-info/LICENSE
pydemic_models-0.1.11.dist-info/WHEEL
pydemic_models-0.1.11.dist-info/METADATA
pydemic_models-0.1.11.dist-info/RECORD
