Metadata-Version: 2.1
Name: pydemic-models
Version: 0.1.11
Summary: Pydemic
Home-page: http://github.com/pydemic/pydemic
License: UNKNOWN
Author: Fábio Macêdo Mendes
Author-email: fabiomacedomendes@gmail.com
Classifier: License :: OSI Approved :: MIT License
Requires-Dist: mundi
Requires-Dist: mundi-demography
Requires-Dist: mundi-healthcare
Requires-Dist: joblib
Requires-Dist: click~=7.0
Requires-Dist: matplotlib~=3.0
Requires-Dist: numpy~=1.0
Requires-Dist: pandas~=1.0
Requires-Dist: requests~=2.0
Requires-Dist: seaborn~=0.10
Requires-Dist: statsmodels
Requires-Dist: black ; extra == "dev"
Requires-Dist: invoke~=1.4 ; extra == "dev"
Requires-Dist: flake8 ; extra == "dev"
Requires-Dist: pytest~=5.4 ; extra == "dev"
Requires-Dist: pytest-cov~=2.8 ; extra == "dev"
Provides-Extra: dev
